Metadata-Version: 2.1
Name: dedupe-fork-eccovia
Version: 2.0.13
Summary: A python library for accurate and scaleable data deduplication and entity-resolution
Home-page: https://github.com/tigerang22/dedupe
Author: Forest Gregg
Author-email: fgregg@datamade.us
Project-URL: Issues, https://github.com/dedupeio/dedupe/issues
Project-URL: Documentation, https://docs.dedupe.io/en/latest/
Project-URL: Examples, https://github.com/dedupeio/dedupe-examples
Project-URL: Twitter, https://twitter.com/DedupeIo
Project-URL: Changelog, https://github.com/dedupeio/dedupe/blob/master/CHANGELOG.md
Project-URL: Mailing List, https://groups.google.com/forum/#!forum/open-source-deduplication
Classifier: Development Status :: 4 - Beta
Classifier: Intended Audience :: Developers
Classifier: Intended Audience :: Science/Research
Classifier: License :: OSI Approved :: MIT License
Classifier: Natural Language :: English
Classifier: Operating System :: MacOS :: MacOS X
Classifier: Operating System :: Microsoft :: Windows
Classifier: Operating System :: POSIX
Classifier: Programming Language :: Cython
Classifier: Programming Language :: Python :: 3
Classifier: Topic :: Software Development :: Libraries :: Python Modules
Classifier: Topic :: Scientific/Engineering
Classifier: Topic :: Scientific/Engineering :: Information Analysis
License-File: LICENSE
Requires-Dist: dedupe-hcluster
Requires-Dist: affinegap (>=1.3)
Requires-Dist: categorical-distance (>=1.9)
Requires-Dist: dedupe-variable-datetime
Requires-Dist: rlr (>=2.4.3)
Requires-Dist: numpy (>=1.13)
Requires-Dist: doublemetaphone
Requires-Dist: highered (>=0.2.0)
Requires-Dist: simplecosine (>=1.2)
Requires-Dist: haversine (>=0.4.1)
Requires-Dist: BTrees (>=4.1.4)
Requires-Dist: zope.index
Requires-Dist: dedupe-Levenshtein-search (==1.4.5)
Requires-Dist: typing-extensions
Requires-Dist: fastcluster ; python_version < "3.10"
